coinmarketcap/__init__.py
coinmarketcap/client.py
coinmarketcap/environment.py
coinmarketcap/endpoints/__init__.py
coinmarketcap/endpoints/cryptocurrency.py
coinmarketcap/endpoints/exchange.py
coinmarketcap/endpoints/global_metrics.py
coinmarketcap/endpoints/parser.py
coinmarketcap/endpoints/tools.py
CoinMarketCapAPI-0.5.dist-info/LICENSE
CoinMarketCapAPI-0.5.dist-info/METADATA
CoinMarketCapAPI-0.5.dist-info/WHEEL
CoinMarketCapAPI-0.5.dist-info/top_level.txt
CoinMarketCapAPI-0.5.dist-info/RECORD
