Metadata-Version: 2.1
Name: CoinMarketCapAPI
Version: 0.5
Summary: Module for fethcing data from CoinMarketCap's v1 API
Home-page: https://github.com/ani071/coinmarketcap
Author: Andreas Isnes Nilsen
Author-email: andnil94@gmail.com
License: UNKNOWN
Keywords: CoinMarketCap,API
Platform: UNKNOWN
Classifier: Programming Language :: Python :: 3
Classifier: License :: OSI Approved :: MIT License
Classifier: Operating System :: OS Independent
